nlp2/__init__.py
nlp2/file.py
nlp2/lm.py
nlp2/panel.py
nlp2/rand.py
nlp2/text.py
nlp2/vectorize.py
nlp2/test/__init__.py
nlp2/test/test_file.py
nlp2/test/test_panel.py
nlp2/test/test_rand.py
nlp2/test/test_text.py
nlp2/test/test_vectorize.py
nlp2/test/test_folder/img1
nlp2/test/test_folder/test.csv
nlp2/test/test_folder/test.json
nlp2-1.9.3.dist-info/LICENSE
nlp2-1.9.3.dist-info/METADATA
nlp2-1.9.3.dist-info/WHEEL
nlp2-1.9.3.dist-info/top_level.txt
nlp2-1.9.3.dist-info/RECORD
