Metadata-Version: 2.1
Name: nlp2
Version: 1.9.3
Summary: Tool for NLP - handle file and text
Home-page: https://github.com/voidful/nlp2
Author: Voidful
Author-email: voidful.stack@gmail.com
Keywords: nlp file io string text mining
Classifier: Development Status :: 4 - Beta
Classifier: Intended Audience :: Developers
Classifier: Topic :: Software Development :: Build Tools
Classifier: License :: OSI Approved :: MIT License
Classifier: Programming Language :: Python :: 3
Classifier: Programming Language :: Python :: 3.4
Classifier: Programming Language :: Python :: 3.5
Classifier: Programming Language :: Python :: 3.6
Classifier: Programming Language :: Python :: 3.7
Classifier: Programming Language :: Python :: 3.8
License-File: LICENSE
